odoo/addons/project_timesheet_time_control_sale/README.rst
odoo/addons/project_timesheet_time_control_sale/__init__.py
odoo/addons/project_timesheet_time_control_sale/__manifest__.py
odoo/addons/project_timesheet_time_control_sale/i18n/it.po
odoo/addons/project_timesheet_time_control_sale/i18n/project_timesheet_time_control_sale.pot
odoo/addons/project_timesheet_time_control_sale/models/__init__.py
odoo/addons/project_timesheet_time_control_sale/models/account_move_line.py
odoo/addons/project_timesheet_time_control_sale/readme/CONTRIBUTORS.rst
odoo/addons/project_timesheet_time_control_sale/readme/DESCRIPTION.rst
odoo/addons/project_timesheet_time_control_sale/static/description/icon.png
odoo/addons/project_timesheet_time_control_sale/static/description/icon.svg
odoo/addons/project_timesheet_time_control_sale/static/description/index.html
odoo13_addon_project_timesheet_time_control_sale-13.0.1.0.1.dev7.dist-info/METADATA
odoo13_addon_project_timesheet_time_control_sale-13.0.1.0.1.dev7.dist-info/WHEEL
odoo13_addon_project_timesheet_time_control_sale-13.0.1.0.1.dev7.dist-info/top_level.txt
odoo13_addon_project_timesheet_time_control_sale-13.0.1.0.1.dev7.dist-info/RECORD
