Metadata-Version: 2.1
Name: odoo13-addon-project-timesheet-time-control-sale
Version: 13.0.1.0.1.dev7
Summary: Make 'Project timesheet time control' and 'Sales Timesheet' work together
Home-page: https://github.com/OCA/project
Author: TAKOBI, Odoo Community Association (OCA)
Author-email: support@odoo-community.org
License: AGPL-3
Platform: UNKNOWN
Classifier: Programming Language :: Python
Classifier: Framework :: Odoo
Classifier: Framework :: Odoo :: 13.0
Classifier: License :: OSI Approved :: GNU Affero General Public License v3
Classifier: Development Status :: 4 - Beta
Requires-Python: >=3.5
Requires-Dist: odoo13-addon-project-timesheet-time-control
Requires-Dist: odoo <13.1dev,>=13.0a
